{
  "day": "2025年3月25日",
  "total": {
    "problem": 29,
    "favorite": 892,
    "answered": 4646
  },
  "count": {
    "favorite": {
      "problem": 677,
      "author": 170
    },
    "answered": {
      "problem": 2952,
      "author": 314,
      "solver": 331
    }
  },
  "top": {
    "problem": {
      "favorite": {
        "count": 16,
        "names": [
          {
            "name": "プッテリア by すずめ",
            "url": "https://puzsq.logicpuzzle.app/share/158700"
          },
          {
            "name": "ヤジリン by 葵",
            "url": "https://puzsq.logicpuzzle.app/share/158637"
          }
        ]
      },
      "answered": {
        "count": 68,
        "names": [
          {
            "name": "ヤジリン by 葵",
            "url": "https://puzsq.logicpuzzle.app/share/158637"
          }
        ]
      }
    },
    "author": {
      "favorite": {
        "count": 67,
        "names": [
          {
            "name": "みんにょこ",
            "url": "https://puzsq.logicpuzzle.app/?author=1247"
          }
        ]
      },
      "answered": {
        "count": 415,
        "names": [
          {
            "name": "anurag",
            "url": "https://puzsq.logicpuzzle.app/?author=2571"
          }
        ]
      }
    },
    "solver": {
      "answered": {
        "count": 167,
        "names": [
          {
            "name": "Aminami",
            "url": "https://puzsq.logicpuzzle.app/?author=2509"
          }
        ]
      }
    }
  }
}
