{
  "day": "2024年4月4日",
  "total": {
    "problem": 53,
    "favorite": 702,
    "answered": 4354
  },
  "count": {
    "favorite": {
      "problem": 505,
      "author": 135
    },
    "answered": {
      "problem": 2725,
      "author": 276,
      "solver": 277
    }
  },
  "top": {
    "problem": {
      "favorite": {
        "count": 13,
        "names": [
          {
            "name": "ノースリー by ph.",
            "url": "https://puzsq.logicpuzzle.app/share/121462"
          },
          {
            "name": "へやわけ by arsenic",
            "url": "https://puzsq.logicpuzzle.app/share/122569"
          },
          {
            "name": "コローン by てけてけ",
            "url": "https://puzsq.logicpuzzle.app/share/122574"
          }
        ]
      },
      "answered": {
        "count": 65,
        "names": [
          {
            "name": "ヤジリン by Zormac",
            "url": "https://puzsq.logicpuzzle.app/share/122538"
          }
        ]
      }
    },
    "author": {
      "favorite": {
        "count": 50,
        "names": [
          {
            "name": "anurag",
            "url": "https://puzsq.logicpuzzle.app/?author=2571"
          }
        ]
      },
      "answered": {
        "count": 388,
        "names": [
          {
            "name": "anurag",
            "url": "https://puzsq.logicpuzzle.app/?author=2571"
          }
        ]
      }
    },
    "solver": {
      "answered": {
        "count": 128,
        "names": [
          {
            "name": "ふくろう",
            "url": "https://puzsq.logicpuzzle.app/?author=272"
          }
        ]
      }
    }
  }
}
