{
  "day": "2024年10月1日",
  "total": {
    "problem": 27,
    "favorite": 516,
    "answered": 4540
  },
  "count": {
    "favorite": {
      "problem": 360,
      "author": 120
    },
    "answered": {
      "problem": 2639,
      "author": 292,
      "solver": 321
    }
  },
  "top": {
    "problem": {
      "favorite": {
        "count": 10,
        "names": [
          {
            "name": "美術館 by stranger_86952",
            "url": "https://puzsq.logicpuzzle.app/share/152346"
          },
          {
            "name": "シャカシャカ by izkdic",
            "url": "https://puzsq.logicpuzzle.app/share/152341"
          }
        ]
      },
      "answered": {
        "count": 83,
        "names": [
          {
            "name": "美術館 by PinkHoodie",
            "url": "https://puzsq.logicpuzzle.app/share/152136"
          }
        ]
      }
    },
    "author": {
      "favorite": {
        "count": 37,
        "names": [
          {
            "name": "鷹野リン",
            "url": "https://puzsq.logicpuzzle.app/?author=584"
          }
        ]
      },
      "answered": {
        "count": 505,
        "names": [
          {
            "name": "anurag",
            "url": "https://puzsq.logicpuzzle.app/?author=2571"
          }
        ]
      }
    },
    "solver": {
      "answered": {
        "count": 189,
        "names": [
          {
            "name": "LaRa",
            "url": "https://puzsq.logicpuzzle.app/?author=3966"
          }
        ]
      }
    }
  }
}
