{
  "day": "2026年1月31日",
  "total": {
    "problem": 30,
    "favorite": 1146,
    "answered": 5694
  },
  "count": {
    "favorite": {
      "problem": 836,
      "author": 220
    },
    "answered": {
      "problem": 3843,
      "author": 371,
      "solver": 401
    }
  },
  "top": {
    "problem": {
      "favorite": {
        "count": 20,
        "names": [
          {
            "name": "へやわけ by たろさ",
            "url": "https://puzsq.logicpuzzle.app/share/168961"
          }
        ]
      },
      "answered": {
        "count": 78,
        "names": [
          {
            "name": "へやわけ by たろさ",
            "url": "https://puzsq.logicpuzzle.app/share/168961"
          }
        ]
      }
    },
    "author": {
      "favorite": {
        "count": 56,
        "names": [
          {
            "name": "ぶすじま",
            "url": "https://puzsq.logicpuzzle.app/?author=511"
          }
        ]
      },
      "answered": {
        "count": 402,
        "names": [
          {
            "name": "anurag",
            "url": "https://puzsq.logicpuzzle.app/?author=2571"
          }
        ]
      }
    },
    "solver": {
      "answered": {
        "count": 249,
        "names": [
          {
            "name": "marek stefanik",
            "url": "https://puzsq.logicpuzzle.app/?author=5000"
          }
        ]
      }
    }
  }
}
