{
  "day": "2026年7月10日",
  "total": {
    "problem": 33,
    "favorite": 978,
    "answered": 5254
  },
  "count": {
    "favorite": {
      "problem": 669,
      "author": 186
    },
    "answered": {
      "problem": 3304,
      "author": 389,
      "solver": 419
    }
  },
  "top": {
    "problem": {
      "favorite": {
        "count": 18,
        "names": [
          {
            "name": "ノースリー by ぴくちゃ",
            "url": "https://puzsq.logicpuzzle.app/share/175000"
          }
        ]
      },
      "answered": {
        "count": 85,
        "names": [
          {
            "name": "美術館 by ON NAME",
            "url": "https://puzsq.logicpuzzle.app/share/174809"
          }
        ]
      }
    },
    "author": {
      "favorite": {
        "count": 45,
        "names": [
          {
            "name": "ぴくちゃ",
            "url": "https://puzsq.logicpuzzle.app/?author=2900"
          },
          {
            "name": "Nuujaka",
            "url": "https://puzsq.logicpuzzle.app/?author=5362"
          }
        ]
      },
      "answered": {
        "count": 236,
        "names": [
          {
            "name": "anurag",
            "url": "https://puzsq.logicpuzzle.app/?author=2571"
          }
        ]
      }
    },
    "solver": {
      "answered": {
        "count": 156,
        "names": [
          {
            "name": "bou",
            "url": "https://puzsq.logicpuzzle.app/?author=5689"
          }
        ]
      }
    }
  }
}
