{
  "day": "2024年6月14日",
  "total": {
    "problem": 81,
    "favorite": 660,
    "answered": 5342
  },
  "count": {
    "favorite": {
      "problem": 445,
      "author": 132
    },
    "answered": {
      "problem": 3203,
      "author": 310,
      "solver": 344
    }
  },
  "top": {
    "problem": {
      "favorite": {
        "count": 16,
        "names": [
          {
            "name": "へやわけ by y888",
            "url": "https://puzsq.logicpuzzle.app/share/125653"
          }
        ]
      },
      "answered": {
        "count": 55,
        "names": [
          {
            "name": "へやわけ by y888",
            "url": "https://puzsq.logicpuzzle.app/share/125653"
          }
        ]
      }
    },
    "author": {
      "favorite": {
        "count": 63,
        "names": [
          {
            "name": "鷹野リン",
            "url": "https://puzsq.logicpuzzle.app/?author=584"
          }
        ]
      },
      "answered": {
        "count": 577,
        "names": [
          {
            "name": "anurag",
            "url": "https://puzsq.logicpuzzle.app/?author=2571"
          }
        ]
      }
    },
    "solver": {
      "answered": {
        "count": 378,
        "names": [
          {
            "name": "落葉子",
            "url": "https://puzsq.logicpuzzle.app/?author=1536"
          }
        ]
      }
    }
  }
}
