{
  "day": "2023年7月21日",
  "total": {
    "problem": 33,
    "favorite": 461,
    "answered": 4046
  },
  "count": {
    "favorite": {
      "problem": 256,
      "author": 89
    },
    "answered": {
      "problem": 1980,
      "author": 234,
      "solver": 276
    }
  },
  "top": {
    "problem": {
      "favorite": {
        "count": 21,
        "names": [
          {
            "name": "ましゅ by K.N.Y.",
            "url": "https://puzsq.logicpuzzle.app/share/111282"
          }
        ]
      },
      "answered": {
        "count": 83,
        "names": [
          {
            "name": "へやわけ by ぶすじま",
            "url": "https://puzsq.logicpuzzle.app/share/111286"
          }
        ]
      }
    },
    "author": {
      "favorite": {
        "count": 47,
        "names": [
          {
            "name": "K.N.Y.",
            "url": "https://puzsq.logicpuzzle.app/?author=74"
          }
        ]
      },
      "answered": {
        "count": 338,
        "names": [
          {
            "name": "K.N.Y.",
            "url": "https://puzsq.logicpuzzle.app/?author=74"
          }
        ]
      }
    },
    "solver": {
      "answered": {
        "count": 131,
        "names": [
          {
            "name": "ugly2333",
            "url": "https://puzsq.logicpuzzle.app/?author=1070"
          }
        ]
      }
    }
  }
}
