{
  "day": "2026年4月29日",
  "total": {
    "problem": 52,
    "favorite": 1247,
    "answered": 6923
  },
  "count": {
    "favorite": {
      "problem": 909,
      "author": 229
    },
    "answered": {
      "problem": 4407,
      "author": 435,
      "solver": 431
    }
  },
  "top": {
    "problem": {
      "favorite": {
        "count": 18,
        "names": [
          {
            "name": "ましゅ by PinkHoodie",
            "url": "https://puzsq.logicpuzzle.app/share/171913"
          }
        ]
      },
      "answered": {
        "count": 65,
        "names": [
          {
            "name": "ましゅ by PinkHoodie",
            "url": "https://puzsq.logicpuzzle.app/share/171913"
          }
        ]
      }
    },
    "author": {
      "favorite": {
        "count": 58,
        "names": [
          {
            "name": "PinkHoodie",
            "url": "https://puzsq.logicpuzzle.app/?author=3187"
          }
        ]
      },
      "answered": {
        "count": 326,
        "names": [
          {
            "name": "PinkHoodie",
            "url": "https://puzsq.logicpuzzle.app/?author=3187"
          }
        ]
      }
    },
    "solver": {
      "answered": {
        "count": 353,
        "names": [
          {
            "name": "solver",
            "url": "https://puzsq.logicpuzzle.app/?author=5358"
          }
        ]
      }
    }
  }
}
