{
  "day": "2024年6月19日",
  "total": {
    "problem": 41,
    "favorite": 738,
    "answered": 5482
  },
  "count": {
    "favorite": {
      "problem": 396,
      "author": 121
    },
    "answered": {
      "problem": 2830,
      "author": 274,
      "solver": 331
    }
  },
  "top": {
    "problem": {
      "favorite": {
        "count": 25,
        "names": [
          {
            "name": "へやわけ by みんにょこ",
            "url": "https://puzsq.logicpuzzle.app/share/126105"
          }
        ]
      },
      "answered": {
        "count": 67,
        "names": [
          {
            "name": "へやわけ by y888",
            "url": "https://puzsq.logicpuzzle.app/share/125781"
          }
        ]
      }
    },
    "author": {
      "favorite": {
        "count": 78,
        "names": [
          {
            "name": "みんにょこ",
            "url": "https://puzsq.logicpuzzle.app/?author=1247"
          }
        ]
      },
      "answered": {
        "count": 538,
        "names": [
          {
            "name": "Zormac",
            "url": "https://puzsq.logicpuzzle.app/?author=2327"
          }
        ]
      }
    },
    "solver": {
      "answered": {
        "count": 181,
        "names": [
          {
            "name": "RN2",
            "url": "https://puzsq.logicpuzzle.app/?author=2964"
          }
        ]
      }
    }
  }
}
