{
  "day": "2025年10月7日",
  "total": {
    "problem": 28,
    "favorite": 891,
    "answered": 5726
  },
  "count": {
    "favorite": {
      "problem": 563,
      "author": 176
    },
    "answered": {
      "problem": 3627,
      "author": 363,
      "solver": 418
    }
  },
  "top": {
    "problem": {
      "favorite": {
        "count": 27,
        "names": [
          {
            "name": "ましゅ by CW-MV",
            "url": "https://puzsq.logicpuzzle.app/share/165097"
          }
        ]
      },
      "answered": {
        "count": 109,
        "names": [
          {
            "name": "ましゅ by CW-MV",
            "url": "https://puzsq.logicpuzzle.app/share/165097"
          }
        ]
      }
    },
    "author": {
      "favorite": {
        "count": 61,
        "names": [
          {
            "name": "鷹野リン",
            "url": "https://puzsq.logicpuzzle.app/?author=584"
          }
        ]
      },
      "answered": {
        "count": 578,
        "names": [
          {
            "name": "anurag",
            "url": "https://puzsq.logicpuzzle.app/?author=2571"
          }
        ]
      }
    },
    "solver": {
      "answered": {
        "count": 147,
        "names": [
          {
            "name": "Salmon",
            "url": "https://puzsq.logicpuzzle.app/?author=3481"
          }
        ]
      }
    }
  }
}
