{
  "day": "2022年11月30日",
  "total": {
    "problem": 30,
    "favorite": 494,
    "answered": 4140
  },
  "count": {
    "favorite": {
      "problem": 304,
      "author": 105
    },
    "answered": {
      "problem": 1900,
      "author": 203,
      "solver": 246
    }
  },
  "top": {
    "problem": {
      "favorite": {
        "count": 13,
        "names": [
          {
            "name": "ヤジリン by coggy",
            "url": "https://puzsq.logicpuzzle.app/share/103113"
          }
        ]
      },
      "answered": {
        "count": 94,
        "names": [
          {
            "name": "美術館 by K.N.Y.",
            "url": "https://puzsq.logicpuzzle.app/share/103114"
          }
        ]
      }
    },
    "author": {
      "favorite": {
        "count": 58,
        "names": [
          {
            "name": "K.N.Y.",
            "url": "https://puzsq.logicpuzzle.app/?author=74"
          }
        ]
      },
      "answered": {
        "count": 388,
        "names": [
          {
            "name": "K.N.Y.",
            "url": "https://puzsq.logicpuzzle.app/?author=74"
          }
        ]
      }
    },
    "solver": {
      "answered": {
        "count": 163,
        "names": [
          {
            "name": "かぶ",
            "url": "https://puzsq.logicpuzzle.app/?author=49"
          }
        ]
      }
    }
  }
}
