{
  "day": "2025年10月26日",
  "total": {
    "problem": 24,
    "favorite": 962,
    "answered": 6512
  },
  "count": {
    "favorite": {
      "problem": 741,
      "author": 189
    },
    "answered": {
      "problem": 4371,
      "author": 397,
      "solver": 386
    }
  },
  "top": {
    "problem": {
      "favorite": {
        "count": 19,
        "names": [
          {
            "name": "シャカシャカ by ss3",
            "url": "https://puzsq.logicpuzzle.app/share/165672"
          },
          {
            "name": "ヤジリン by anurag",
            "url": "https://puzsq.logicpuzzle.app/share/165674"
          },
          {
            "name": "ヤジリン by endagorion",
            "url": "https://puzsq.logicpuzzle.app/share/165676"
          }
        ]
      },
      "answered": {
        "count": 96,
        "names": [
          {
            "name": "ヤジリン by anurag",
            "url": "https://puzsq.logicpuzzle.app/share/165674"
          }
        ]
      }
    },
    "author": {
      "favorite": {
        "count": 70,
        "names": [
          {
            "name": "anurag",
            "url": "https://puzsq.logicpuzzle.app/?author=2571"
          }
        ]
      },
      "answered": {
        "count": 563,
        "names": [
          {
            "name": "anurag",
            "url": "https://puzsq.logicpuzzle.app/?author=2571"
          }
        ]
      }
    },
    "solver": {
      "answered": {
        "count": 389,
        "names": [
          {
            "name": "落葉子",
            "url": "https://puzsq.logicpuzzle.app/?author=1536"
          }
        ]
      }
    }
  }
}
