{
  "day": "2025年9月20日",
  "total": {
    "problem": 28,
    "favorite": 916,
    "answered": 4506
  },
  "count": {
    "favorite": {
      "problem": 671,
      "author": 198
    },
    "answered": {
      "problem": 2770,
      "author": 357,
      "solver": 373
    }
  },
  "top": {
    "problem": {
      "favorite": {
        "count": 18,
        "names": [
          {
            "name": "へやわけ by サンゴ三号さん",
            "url": "https://puzsq.logicpuzzle.app/share/164509"
          },
          {
            "name": "シンプルループ by NoWiz",
            "url": "https://puzsq.logicpuzzle.app/share/164527"
          }
        ]
      },
      "answered": {
        "count": 82,
        "names": [
          {
            "name": "シンプルループ by NoWiz",
            "url": "https://puzsq.logicpuzzle.app/share/164527"
          }
        ]
      }
    },
    "author": {
      "favorite": {
        "count": 64,
        "names": [
          {
            "name": "anurag",
            "url": "https://puzsq.logicpuzzle.app/?author=2571"
          }
        ]
      },
      "answered": {
        "count": 497,
        "names": [
          {
            "name": "anurag",
            "url": "https://puzsq.logicpuzzle.app/?author=2571"
          }
        ]
      }
    },
    "solver": {
      "answered": {
        "count": 214,
        "names": [
          {
            "name": "rin204",
            "url": "https://puzsq.logicpuzzle.app/?author=2442"
          }
        ]
      }
    }
  }
}
