{
  "day": "2024年12月19日",
  "total": {
    "problem": 59,
    "favorite": 846,
    "answered": 4307
  },
  "count": {
    "favorite": {
      "problem": 567,
      "author": 159
    },
    "answered": {
      "problem": 2609,
      "author": 305,
      "solver": 332
    }
  },
  "top": {
    "problem": {
      "favorite": {
        "count": 16,
        "names": [
          {
            "name": "ましゅ by ON NAME",
            "url": "https://puzsq.logicpuzzle.app/share/155345"
          }
        ]
      },
      "answered": {
        "count": 76,
        "names": [
          {
            "name": "ヤジリン by Zormac",
            "url": "https://puzsq.logicpuzzle.app/share/155210"
          }
        ]
      }
    },
    "author": {
      "favorite": {
        "count": 56,
        "names": [
          {
            "name": "y888",
            "url": "https://puzsq.logicpuzzle.app/?author=3102"
          }
        ]
      },
      "answered": {
        "count": 282,
        "names": [
          {
            "name": "PinkHoodie",
            "url": "https://puzsq.logicpuzzle.app/?author=3187"
          }
        ]
      }
    },
    "solver": {
      "answered": {
        "count": 144,
        "names": [
          {
            "name": "MF",
            "url": "https://puzsq.logicpuzzle.app/?author=91"
          }
        ]
      }
    }
  }
}
