{
  "day": "2023年5月23日",
  "total": {
    "problem": 29,
    "favorite": 436,
    "answered": 4575
  },
  "count": {
    "favorite": {
      "problem": 189,
      "author": 74
    },
    "answered": {
      "problem": 2173,
      "author": 235,
      "solver": 277
    }
  },
  "top": {
    "problem": {
      "favorite": {
        "count": 15,
        "names": [
          {
            "name": "ヤジリン by chip",
            "url": "https://puzsq.logicpuzzle.app/share/108973"
          }
        ]
      },
      "answered": {
        "count": 89,
        "names": [
          {
            "name": "へやわけ by coggy",
            "url": "https://puzsq.logicpuzzle.app/share/108564"
          }
        ]
      }
    },
    "author": {
      "favorite": {
        "count": 74,
        "names": [
          {
            "name": "みんにょこ",
            "url": "https://puzsq.logicpuzzle.app/?author=1247"
          }
        ]
      },
      "answered": {
        "count": 486,
        "names": [
          {
            "name": "みんにょこ",
            "url": "https://puzsq.logicpuzzle.app/?author=1247"
          }
        ]
      }
    },
    "solver": {
      "answered": {
        "count": 109,
        "names": [
          {
            "name": "kawatea",
            "url": "https://puzsq.logicpuzzle.app/?author=1468"
          }
        ]
      }
    }
  }
}
