{
  "day": "2022年12月3日",
  "total": {
    "problem": 34,
    "favorite": 658,
    "answered": 4461
  },
  "count": {
    "favorite": {
      "problem": 366,
      "author": 114
    },
    "answered": {
      "problem": 1751,
      "author": 215,
      "solver": 252
    }
  },
  "top": {
    "problem": {
      "favorite": {
        "count": 18,
        "names": [
          {
            "name": "マティーニ by takmu",
            "url": "https://puzsq.logicpuzzle.app/share/103267"
          }
        ]
      },
      "answered": {
        "count": 74,
        "names": [
          {
            "name": "カクテルランプ by カルコゲン",
            "url": "https://puzsq.logicpuzzle.app/share/103079"
          }
        ]
      }
    },
    "author": {
      "favorite": {
        "count": 49,
        "names": [
          {
            "name": "_AtomicNeoN_",
            "url": "https://puzsq.logicpuzzle.app/?author=358"
          }
        ]
      },
      "answered": {
        "count": 331,
        "names": [
          {
            "name": "みんにょこ",
            "url": "https://puzsq.logicpuzzle.app/?author=1247"
          }
        ]
      }
    },
    "solver": {
      "answered": {
        "count": 136,
        "names": [
          {
            "name": "あまからとう",
            "url": "https://puzsq.logicpuzzle.app/?author=453"
          }
        ]
      }
    }
  }
}
